Metadata-Version: 2.1
Name: graphinx
Version: 0.0
Summary: Functions to draw beautigul plots from dataframes
Author-email: hernangarciamayoral@gmail.com
License: UNKNOWN
Platform: UNKNOWN
